{"assets":{"D85A9480C71E28EC976F819F398CD19E":{"type":"texture","index":7,"assetRequest":{"type":"slide","state":"incoming","slide":"75E373C3-02CD-4E88-895E-9DFA4EB5F8F3"},"url":{"web":"assets/D85A9480C71E28EC976F819F398CD19E.svg"},"width":1920,"height":1080},"82DDE1CFE26139CDC4AB9DA49C208CB5":{"type":"texture","index":6,"assetRequest":{"type":"slide","state":"outgoing","slide":"74F3BA3C-C577-46E4-835E-1E95E6C4F8AD"},"url":{"web":"assets/82DDE1CFE26139CDC4AB9DA49C208CB5.svg"},"width":1920,"height":1080}},"events":[{"effects":[{"beginTime":0,"baseLayer":{"animations":[],"initialState":{"affineTransform":[1,0,0,1,0,0],"masksToBounds":false,"rotation":0,"scale":1,"position":{"pointX":960,"pointY":540},"width":1920,"sublayerTransform":[1,0,0,0,0,1,0,0,0,0,1,0,0,0,0,1],"contentsRect":{"y":0,"x":0,"width":1,"height":1},"opacity":1,"edgeAntialiasingMask":251658240,"height":1080,"hidden":false,"anchorPoint":{"pointX":0.5,"pointY":0.5}},"objectID":"0","layers":[{"animations":[],"initialState":{"affineTransform":[1,0,0,1,0,0],"masksToBounds":false,"rotation":0,"scale":1,"position":{"pointX":960,"pointY":540},"width":1920,"sublayerTransform":[1,0,0,0,0,1,0,0,0,0,1,-0.0003500791246677598,0,0,0,1],"contentsRect":{"y":0,"x":0,"width":1,"height":1},"opacity":1,"edgeAntialiasingMask":251658240,"height":1080,"hidden":false,"anchorPoint":{"pointX":0.5,"pointY":0.5}},"layers":[{"animations":[],"layers":[],"initialState":{"affineTransform":[1,0,0,1,0,0],"masksToBounds":false,"rotation":0,"scale":1,"position":{"pointX":960,"pointY":540},"width":1920,"sublayerTransform":[1,0,0,0,0,1,0,0,0,0,1,0,0,0,0,1],"contentsRect":{"y":0,"x":0,"width":1,"height":1},"opacity":1,"edgeAntialiasingMask":0,"height":1080,"hidden":false,"anchorPoint":{"pointX":0.5,"pointY":0.5}},"texture":"D85A9480C71E28EC976F819F398CD19E"},{"animations":[{"timeOffset":0,"from":{"scalar":false},"beginTime":0,"repeatCount":0,"fillMode":"both","property":"hidden","autoreverses":false,"duration":0.01,"to":{"scalar":true}}],"layers":[],"initialState":{"affineTransform":[1,0,0,1,0,0],"masksToBounds":false,"rotation":0,"scale":1,"position":{"pointX":960,"pointY":540},"width":1920,"sublayerTransform":[1,0,0,0,0,1,0,0,0,0,1,0,0,0,0,1],"contentsRect":{"y":0,"x":0,"width":1,"height":1},"opacity":1,"edgeAntialiasingMask":0,"height":1080,"hidden":false,"anchorPoint":{"pointX":0.5,"pointY":0.5}},"texture":"82DDE1CFE26139CDC4AB9DA49C208CB5"}]}]},"effects":[],"duration":0.01,"type":"transition","name":"none","objectID":"0"}],"automaticPlay":false,"hyperlinks":[],"accessibility":[{"text":"Inside-Out-Disgust-193904.jpg","targetRectangle":{"y":220,"x":64,"width":416,"height":640}},{"text":"Ephemeral","targetRectangle":{"y":864.3218088150024,"x":121.4000000953674,"width":301.2,"height":116.0993041992188}},{"text":"Data Structures","targetRectangle":{"y":23.99999928474426,"x":621.0000057220459,"width":678,"height":173.6489562988281}},{"text":"b3d1bf86c2c7aa22aad2006518b75106.jpg","targetRectangle":{"y":220,"x":1440,"width":416,"height":640}},{"text":"Partially Persistent","targetRectangle":{"y":864.3218088150024,"x":682.5999994277954,"width":554.8000000000002,"height":116.0993041992188}},{"text":"SADNESS_Fullbody_Render.png","targetRectangle":{"y":220.2059478759766,"x":710,"width":500,"height":639.588134765625}},{"text":"Fully Persistent","targetRectangle":{"y":864.3218088150024,"x":1425.29999256134,"width":445.4000000000001,"height":116.0993041992188}}],"baseLayer":{"animations":[],"initialState":{"affineTransform":[1,0,0,1,0,0],"masksToBounds":false,"rotation":0,"scale":1,"position":{"pointX":960,"pointY":540},"width":1920,"sublayerTransform":[1,0,0,0,0,1,0,0,0,0,1,0,0,0,0,1],"contentsRect":{"y":0,"x":0,"width":1,"height":1},"opacity":1,"edgeAntialiasingMask":251658240,"height":1080,"hidden":false,"anchorPoint":{"pointX":0.5,"pointY":0.5}},"objectID":"0","layers":[{"animations":[],"initialState":{"affineTransform":[1,0,0,1,0,0],"masksToBounds":false,"rotation":0,"scale":1,"position":{"pointX":960,"pointY":540},"width":1920,"sublayerTransform":[1,0,0,0,0,1,0,0,0,0,1,-0.0003500791246677598,0,0,0,1],"contentsRect":{"y":0,"x":0,"width":1,"height":1},"opacity":1,"edgeAntialiasingMask":251658240,"height":1080,"hidden":false,"anchorPoint":{"pointX":0.5,"pointY":0.5}},"layers":[{"animations":[],"layers":[],"initialState":{"affineTransform":[1,0,0,1,0,0],"masksToBounds":false,"rotation":0,"scale":1,"position":{"pointX":960,"pointY":540},"width":1920,"sublayerTransform":[1,0,0,0,0,1,0,0,0,0,1,0,0,0,0,1],"contentsRect":{"y":0,"x":0,"width":1,"height":1},"opacity":1,"edgeAntialiasingMask":0,"height":1080,"hidden":false,"anchorPoint":{"pointX":0.5,"pointY":0.5}},"texture":"82DDE1CFE26139CDC4AB9DA49C208CB5"}]}]}}]}